LICENSE
MANIFEST.in
README.rst
setup.py
mempamal/__init__.py
mempamal/arguments.py
mempamal/configuration.py
mempamal/crossval.py
mempamal/dynamic.py
mempamal/gridsearch.py
mempamal/workflow.py
mempamal.egg-info/PKG-INFO
mempamal.egg-info/SOURCES.txt
mempamal.egg-info/dependency_links.txt
mempamal.egg-info/requires.txt
mempamal.egg-info/top_level.txt
mempamal/datasets/__init__.py
mempamal/datasets/iris.py
mempamal/examples/MEmPaMaL_first_example.ipynb
mempamal/examples/MEmPaMaL_fourth_example.ipynb
mempamal/examples/MEmPaMaL_second_example.ipynb
mempamal/examples/MEmPaMaL_third_example.ipynb
mempamal/examples/__init__.py
mempamal/examples/elasticnet_parsimony.py
mempamal/examples/first_example.py
mempamal/examples/parameters_grid.py
mempamal/scripts/__init__.py
mempamal/scripts/inner_reducer.py
mempamal/scripts/mapper.py
mempamal/scripts/outer_reducer.py