Metadata-Version: 1.1
Name: mempamal
Version: 0.1.5
Summary: MEMPAMAL: Means for EMbarrassingly PArallel MAchine Learning
Home-page: https://github.com/BenoitDamota/mempamal
Author: Benoit Da Mota
Author-email: damota.benoit@gmail.com
License: BSD 3-clause
Platform: UNKNOWN
Classifier: Development Status :: 3 - Alpha
Classifier: Intended Audience :: Science/Research
Classifier: Intended Audience :: Developers
Classifier: License :: OSI Approved :: BSD License
Classifier: Operating System :: Unix
Classifier: Operating System :: POSIX :: Linux
Classifier: Programming Language :: Python
Classifier: Topic :: Software Development
Classifier: Topic :: Scientific/Engineering
Classifier: Topic :: Software Development :: Libraries :: Python Modules
